containers/environment_pipeline.yml
containers/multiqc_config.yaml
containers/seqnado.png
containers/seqnado_ml_cpu.def
containers/seqnado_ml_gpu.def
containers/seqnado_pipeline.def
containers/old/environment_extra.yml
containers/old/environment_report.yml
containers/old/environment_slim.yml
containers/old/lanceotron-mcc.def
containers/old/seqnado_extra.def
containers/old/seqnado_mcc.def
containers/old/seqnado_pipeline.def
containers/old/seqnado_report.def
docs/cluster_config.md
docs/faq.md
docs/index.md
docs/installation.md
docs/pipeline.md
seqnado/__init__.py
seqnado/_version.py
seqnado/cli.py
seqnado/config.py
seqnado/design.py
seqnado/helpers.py
seqnado/init.sh
seqnado/data/__init__.py
seqnado/data/geo_upload_instructions.txt
seqnado/data/logo.txt
seqnado/workflow/__init__.py
seqnado/workflow/snakefile_atac
seqnado/workflow/snakefile_build_index
seqnado/workflow/snakefile_cat
seqnado/workflow/snakefile_chip
seqnado/workflow/snakefile_crispr
seqnado/workflow/snakefile_mcc
seqnado/workflow/snakefile_meth
seqnado/workflow/snakefile_rna
seqnado/workflow/snakefile_snp
seqnado/workflow/config/__init__.py
seqnado/workflow/config/config.yaml.jinja
seqnado/workflow/config/deseq2.qmd.jinja
seqnado/workflow/config/genomes_template.json
seqnado/workflow/config/preset_genomes.json
seqnado/workflow/config/tool_options_base.yml
seqnado/workflow/config/tool_options_crispr.yml
seqnado/workflow/config/tool_options_mcc.yml
seqnado/workflow/config/tool_options_meth.yml
seqnado/workflow/config/tool_options_rna.yml
seqnado/workflow/config/tool_options_snp.yml
seqnado/workflow/envs/environment.yml
seqnado/workflow/envs/profiles/profile_singularity/config.yaml
seqnado/workflow/envs/profiles/profile_slurm_singularity/config.yaml
seqnado/workflow/envs/profiles/profile_test/config.v8+.yaml
seqnado/workflow/rules/align.smk
seqnado/workflow/rules/align_rna.smk
seqnado/workflow/rules/alignment_counts.smk
seqnado/workflow/rules/alignment_post_processing.smk
seqnado/workflow/rules/common.smk
seqnado-0.7.6.dist-info/licenses/LICENSE
seqnado-0.7.6.dist-info/METADATA
seqnado-0.7.6.dist-info/WHEEL
seqnado-0.7.6.dist-info/entry_points.txt
seqnado-0.7.6.dist-info/top_level.txt
seqnado-0.7.6.dist-info/RECORD
