Metadata-Version: 2.4
Name: seqnado
Version: 0.7.6
Summary: Pipelines for genomics analysis
Author-email: Alastair Smith <alastair.smith@ndcls.ox.ac.uk>, Catherine Chahrour <catherine.chahrour@msdtc.ox.ac.uk>
License: GNU GENERAL PUBLIC LICENSE
Project-URL: Homepage, https://github.com/alsmith151/seqnado
Requires-Python: >=3.10
License-File: LICENSE
Requires-Dist: click
Requires-Dist: cookiecutter
Requires-Dist: pandas
Requires-Dist: pandera
Requires-Dist: pulp<=3.2.1
Requires-Dist: pydantic
Requires-Dist: pyyaml
Requires-Dist: seaborn
Requires-Dist: snakemake-wrapper-utils
Requires-Dist: snakemake<9,>=8
Requires-Dist: snakemake-executor-plugin-slurm
Requires-Dist: tracknado
Requires-Dist: wget
Dynamic: license-file
